{"frames": [

{
	"filename": "bible/fly",
	"frame": {"x":82,"y":0,"w":22,"h":28},
	"rotated": false,
	"trimmed": false,
	"spriteSourceSize": {"x":0,"y":0,"w":22,"h":28},
	"sourceSize": {"w":22,"h":28}
},
{
	"filename": "brick",
	"frame": {"x":0,"y":0,"w":18,"h":10},
	"rotated": false,
	"trimmed": false,
	"spriteSourceSize": {"x":0,"y":0,"w":18,"h":10},
	"sourceSize": {"w":18,"h":10}
},
{
	"filename": "caleb/bend",
	"frame": {"x":480,"y":32,"w":32,"h":32},
	"rotated": false,
	"trimmed": false,
	"spriteSourceSize": {"x":0,"y":0,"w":32,"h":32},
	"sourceSize": {"w":32,"h":32}
},
{
	"filename": "caleb/bendBig",
	"frame": {"x":640,"y":128,"w":64,"h":64},
	"rotated": false,
	"trimmed": false,
	"spriteSourceSize": {"x":0,"y":0,"w":64,"h":64},
	"sourceSize": {"w":64,"h":64}
},
{
	"filename": "caleb/bendSuper",
	"frame": {"x":704,"y":128,"w":64,"h":64},
	"rotated": false,
	"trimmed": false,
	"spriteSourceSize": {"x":0,"y":0,"w":64,"h":64},
	"sourceSize": {"w":64,"h":64}
},
{
	"filename": "caleb/climb1",
	"frame": {"x":224,"y":32,"w":32,"h":32},
	"rotated": false,
	"trimmed": false,
	"spriteSourceSize": {"x":0,"y":0,"w":32,"h":32},
	"sourceSize": {"w":32,"h":32}
},
{
	"filename": "caleb/climb2",
	"frame": {"x":160,"y":32,"w":32,"h":32},
	"rotated": false,
	"trimmed": false,
	"spriteSourceSize": {"x":0,"y":0,"w":32,"h":32},
	"sourceSize": {"w":32,"h":32}
},
{
	"filename": "caleb/climbBig1",
	"frame": {"x":768,"y":128,"w":64,"h":64},
	"rotated": false,
	"trimmed": false,
	"spriteSourceSize": {"x":0,"y":0,"w":64,"h":64},
	"sourceSize": {"w":64,"h":64}
},
{
	"filename": "caleb/climbBig2",
	"frame": {"x":192,"y":192,"w":64,"h":64},
	"rotated": false,
	"trimmed": false,
	"spriteSourceSize": {"x":0,"y":0,"w":64,"h":64},
	"sourceSize": {"w":64,"h":64}
},
{
	"filename": "caleb/climbSuper1",
	"frame": {"x":0,"y":192,"w":64,"h":64},
	"rotated": false,
	"trimmed": false,
	"spriteSourceSize": {"x":0,"y":0,"w":64,"h":64},
	"sourceSize": {"w":64,"h":64}
},
{
	"filename": "caleb/climbSuper2",
	"frame": {"x":64,"y":192,"w":64,"h":64},
	"rotated": false,
	"trimmed": false,
	"spriteSourceSize": {"x":0,"y":0,"w":64,"h":64},
	"sourceSize": {"w":64,"h":64}
},
{
	"filename": "caleb/death",
	"frame": {"x":864,"y":32,"w":32,"h":32},
	"rotated": false,
	"trimmed": false,
	"spriteSourceSize": {"x":0,"y":0,"w":32,"h":32},
	"sourceSize": {"w":32,"h":32}
},
{
	"filename": "caleb/half",
	"frame": {"x":240,"y":64,"w":32,"h":64},
	"rotated": false,
	"trimmed": false,
	"spriteSourceSize": {"x":0,"y":0,"w":32,"h":64},
	"sourceSize": {"w":32,"h":64}
},
{
	"filename": "caleb/jump",
	"frame": {"x":832,"y":32,"w":32,"h":32},
	"rotated": false,
	"trimmed": false,
	"spriteSourceSize": {"x":0,"y":0,"w":32,"h":32},
	"sourceSize": {"w":32,"h":32}
},
{
	"filename": "caleb/jumpBig",
	"frame": {"x":896,"y":128,"w":64,"h":64},
	"rotated": false,
	"trimmed": false,
	"spriteSourceSize": {"x":0,"y":0,"w":64,"h":64},
	"sourceSize": {"w":64,"h":64}
},
{
	"filename": "caleb/jumpSuper",
	"frame": {"x":128,"y":192,"w":64,"h":64},
	"rotated": false,
	"trimmed": false,
	"spriteSourceSize": {"x":0,"y":0,"w":64,"h":64},
	"sourceSize": {"w":64,"h":64}
},
{
	"filename": "caleb/stand",
	"frame": {"x":672,"y":32,"w":32,"h":32},
	"rotated": false,
	"trimmed": false,
	"spriteSourceSize": {"x":0,"y":0,"w":32,"h":32},
	"sourceSize": {"w":32,"h":32}
},
{
	"filename": "caleb/standBig",
	"frame": {"x":832,"y":128,"w":64,"h":64},
	"rotated": false,
	"trimmed": false,
	"spriteSourceSize": {"x":0,"y":0,"w":64,"h":64},
	"sourceSize": {"w":64,"h":64}
},
{
	"filename": "caleb/standSuper",
	"frame": {"x":512,"y":128,"w":64,"h":64},
	"rotated": false,
	"trimmed": false,
	"spriteSourceSize": {"x":0,"y":0,"w":64,"h":64},
	"sourceSize": {"w":64,"h":64}
},
{
	"filename": "caleb/turn",
	"frame": {"x":800,"y":32,"w":32,"h":32},
	"rotated": false,
	"trimmed": false,
	"spriteSourceSize": {"x":0,"y":0,"w":32,"h":32},
	"sourceSize": {"w":32,"h":32}
},
{
	"filename": "caleb/turnBig",
	"frame": {"x":448,"y":192,"w":64,"h":64},
	"rotated": false,
	"trimmed": false,
	"spriteSourceSize": {"x":0,"y":0,"w":64,"h":64},
	"sourceSize": {"w":64,"h":64}
},
{
	"filename": "caleb/turnSuper",
	"frame": {"x":512,"y":192,"w":64,"h":64},
	"rotated": false,
	"trimmed": false,
	"spriteSourceSize": {"x":0,"y":0,"w":64,"h":64},
	"sourceSize": {"w":64,"h":64}
},
{
	"filename": "caleb/walk1",
	"frame": {"x":608,"y":32,"w":32,"h":32},
	"rotated": false,
	"trimmed": false,
	"spriteSourceSize": {"x":0,"y":0,"w":32,"h":32},
	"sourceSize": {"w":32,"h":32}
},
{
	"filename": "caleb/walk2",
	"frame": {"x":736,"y":32,"w":32,"h":32},
	"rotated": false,
	"trimmed": false,
	"spriteSourceSize": {"x":0,"y":0,"w":32,"h":32},
	"sourceSize": {"w":32,"h":32}
},
{
	"filename": "caleb/walk3",
	"frame": {"x":768,"y":32,"w":32,"h":32},
	"rotated": false,
	"trimmed": false,
	"spriteSourceSize": {"x":0,"y":0,"w":32,"h":32},
	"sourceSize": {"w":32,"h":32}
},
{
	"filename": "caleb/walkBig1",
	"frame": {"x":640,"y":192,"w":64,"h":64},
	"rotated": false,
	"trimmed": false,
	"spriteSourceSize": {"x":0,"y":0,"w":64,"h":64},
	"sourceSize": {"w":64,"h":64}
},
{
	"filename": "caleb/walkBig2",
	"frame": {"x":576,"y":192,"w":64,"h":64},
	"rotated": false,
	"trimmed": false,
	"spriteSourceSize": {"x":0,"y":0,"w":64,"h":64},
	"sourceSize": {"w":64,"h":64}
},
{
	"filename": "caleb/walkBig3",
	"frame": {"x":320,"y":192,"w":64,"h":64},
	"rotated": false,
	"trimmed": false,
	"spriteSourceSize": {"x":0,"y":0,"w":64,"h":64},
	"sourceSize": {"w":64,"h":64}
},
{
	"filename": "caleb/walkSuper1",
	"frame": {"x":384,"y":192,"w":64,"h":64},
	"rotated": false,
	"trimmed": false,
	"spriteSourceSize": {"x":0,"y":0,"w":64,"h":64},
	"sourceSize": {"w":64,"h":64}
},
{
	"filename": "caleb/walkSuper2",
	"frame": {"x":256,"y":192,"w":64,"h":64},
	"rotated": false,
	"trimmed": false,
	"spriteSourceSize": {"x":0,"y":0,"w":64,"h":64},
	"sourceSize": {"w":64,"h":64}
},
{
	"filename": "caleb/walkSuper3",
	"frame": {"x":448,"y":128,"w":64,"h":64},
	"rotated": false,
	"trimmed": false,
	"spriteSourceSize": {"x":0,"y":0,"w":64,"h":64},
	"sourceSize": {"w":64,"h":64}
},
{
	"filename": "candy/blue1",
	"frame": {"x":916,"y":0,"w":28,"h":32},
	"rotated": false,
	"trimmed": false,
	"spriteSourceSize": {"x":0,"y":0,"w":28,"h":32},
	"sourceSize": {"w":28,"h":32}
},
{
	"filename": "candy/blue2",
	"frame": {"x":888,"y":0,"w":28,"h":32},
	"rotated": false,
	"trimmed": false,
	"spriteSourceSize": {"x":0,"y":0,"w":28,"h":32},
	"sourceSize": {"w":28,"h":32}
},
{
	"filename": "candy/blue3",
	"frame": {"x":692,"y":0,"w":28,"h":32},
	"rotated": false,
	"trimmed": false,
	"spriteSourceSize": {"x":0,"y":0,"w":28,"h":32},
	"sourceSize": {"w":28,"h":32}
},
{
	"filename": "candy/blue4",
	"frame": {"x":300,"y":0,"w":28,"h":32},
	"rotated": false,
	"trimmed": false,
	"spriteSourceSize": {"x":0,"y":0,"w":28,"h":32},
	"sourceSize": {"w":28,"h":32}
},
{
	"filename": "candy/blue5",
	"frame": {"x":356,"y":0,"w":28,"h":32},
	"rotated": false,
	"trimmed": false,
	"spriteSourceSize": {"x":0,"y":0,"w":28,"h":32},
	"sourceSize": {"w":28,"h":32}
},
{
	"filename": "candy/blue6",
	"frame": {"x":440,"y":0,"w":28,"h":32},
	"rotated": false,
	"trimmed": false,
	"spriteSourceSize": {"x":0,"y":0,"w":28,"h":32},
	"sourceSize": {"w":28,"h":32}
},
{
	"filename": "candy/green1",
	"frame": {"x":384,"y":0,"w":28,"h":32},
	"rotated": false,
	"trimmed": false,
	"spriteSourceSize": {"x":0,"y":0,"w":28,"h":32},
	"sourceSize": {"w":28,"h":32}
},
{
	"filename": "candy/green2",
	"frame": {"x":272,"y":0,"w":28,"h":32},
	"rotated": false,
	"trimmed": false,
	"spriteSourceSize": {"x":0,"y":0,"w":28,"h":32},
	"sourceSize": {"w":28,"h":32}
},
{
	"filename": "candy/green3",
	"frame": {"x":328,"y":0,"w":28,"h":32},
	"rotated": false,
	"trimmed": false,
	"spriteSourceSize": {"x":0,"y":0,"w":28,"h":32},
	"sourceSize": {"w":28,"h":32}
},
{
	"filename": "candy/green4",
	"frame": {"x":216,"y":0,"w":28,"h":32},
	"rotated": false,
	"trimmed": false,
	"spriteSourceSize": {"x":0,"y":0,"w":28,"h":32},
	"sourceSize": {"w":28,"h":32}
},
{
	"filename": "candy/green5",
	"frame": {"x":104,"y":0,"w":28,"h":32},
	"rotated": false,
	"trimmed": false,
	"spriteSourceSize": {"x":0,"y":0,"w":28,"h":32},
	"sourceSize": {"w":28,"h":32}
},
{
	"filename": "candy/green6",
	"frame": {"x":132,"y":0,"w":28,"h":32},
	"rotated": false,
	"trimmed": false,
	"spriteSourceSize": {"x":0,"y":0,"w":28,"h":32},
	"sourceSize": {"w":28,"h":32}
},
{
	"filename": "candy/orange1",
	"frame": {"x":244,"y":0,"w":28,"h":32},
	"rotated": false,
	"trimmed": false,
	"spriteSourceSize": {"x":0,"y":0,"w":28,"h":32},
	"sourceSize": {"w":28,"h":32}
},
{
	"filename": "candy/orange2",
	"frame": {"x":188,"y":0,"w":28,"h":32},
	"rotated": false,
	"trimmed": false,
	"spriteSourceSize": {"x":0,"y":0,"w":28,"h":32},
	"sourceSize": {"w":28,"h":32}
},
{
	"filename": "candy/orange3",
	"frame": {"x":160,"y":0,"w":28,"h":32},
	"rotated": false,
	"trimmed": false,
	"spriteSourceSize": {"x":0,"y":0,"w":28,"h":32},
	"sourceSize": {"w":28,"h":32}
},
{
	"filename": "candy/orange4",
	"frame": {"x":412,"y":0,"w":28,"h":32},
	"rotated": false,
	"trimmed": false,
	"spriteSourceSize": {"x":0,"y":0,"w":28,"h":32},
	"sourceSize": {"w":28,"h":32}
},
{
	"filename": "candy/orange5",
	"frame": {"x":524,"y":0,"w":28,"h":32},
	"rotated": false,
	"trimmed": false,
	"spriteSourceSize": {"x":0,"y":0,"w":28,"h":32},
	"sourceSize": {"w":28,"h":32}
},
{
	"filename": "candy/orange6",
	"frame": {"x":468,"y":0,"w":28,"h":32},
	"rotated": false,
	"trimmed": false,
	"spriteSourceSize": {"x":0,"y":0,"w":28,"h":32},
	"sourceSize": {"w":28,"h":32}
},
{
	"filename": "candy/red1",
	"frame": {"x":748,"y":0,"w":28,"h":32},
	"rotated": false,
	"trimmed": false,
	"spriteSourceSize": {"x":0,"y":0,"w":28,"h":32},
	"sourceSize": {"w":28,"h":32}
},
{
	"filename": "candy/red2",
	"frame": {"x":832,"y":0,"w":28,"h":32},
	"rotated": false,
	"trimmed": false,
	"spriteSourceSize": {"x":0,"y":0,"w":28,"h":32},
	"sourceSize": {"w":28,"h":32}
},
{
	"filename": "candy/red3",
	"frame": {"x":776,"y":0,"w":28,"h":32},
	"rotated": false,
	"trimmed": false,
	"spriteSourceSize": {"x":0,"y":0,"w":28,"h":32},
	"sourceSize": {"w":28,"h":32}
},
{
	"filename": "candy/red4",
	"frame": {"x":804,"y":0,"w":28,"h":32},
	"rotated": false,
	"trimmed": false,
	"spriteSourceSize": {"x":0,"y":0,"w":28,"h":32},
	"sourceSize": {"w":28,"h":32}
},
{
	"filename": "candy/red5",
	"frame": {"x":720,"y":0,"w":28,"h":32},
	"rotated": false,
	"trimmed": false,
	"spriteSourceSize": {"x":0,"y":0,"w":28,"h":32},
	"sourceSize": {"w":28,"h":32}
},
{
	"filename": "candy/red6",
	"frame": {"x":664,"y":0,"w":28,"h":32},
	"rotated": false,
	"trimmed": false,
	"spriteSourceSize": {"x":0,"y":0,"w":28,"h":32},
	"sourceSize": {"w":28,"h":32}
},
{
	"filename": "candy/yellow1",
	"frame": {"x":496,"y":0,"w":28,"h":32},
	"rotated": false,
	"trimmed": false,
	"spriteSourceSize": {"x":0,"y":0,"w":28,"h":32},
	"sourceSize": {"w":28,"h":32}
},
{
	"filename": "candy/yellow2",
	"frame": {"x":552,"y":0,"w":28,"h":32},
	"rotated": false,
	"trimmed": false,
	"spriteSourceSize": {"x":0,"y":0,"w":28,"h":32},
	"sourceSize": {"w":28,"h":32}
},
{
	"filename": "candy/yellow3",
	"frame": {"x":636,"y":0,"w":28,"h":32},
	"rotated": false,
	"trimmed": false,
	"spriteSourceSize": {"x":0,"y":0,"w":28,"h":32},
	"sourceSize": {"w":28,"h":32}
},
{
	"filename": "candy/yellow4",
	"frame": {"x":580,"y":0,"w":28,"h":32},
	"rotated": false,
	"trimmed": false,
	"spriteSourceSize": {"x":0,"y":0,"w":28,"h":32},
	"sourceSize": {"w":28,"h":32}
},
{
	"filename": "candy/yellow5",
	"frame": {"x":608,"y":0,"w":28,"h":32},
	"rotated": false,
	"trimmed": false,
	"spriteSourceSize": {"x":0,"y":0,"w":28,"h":32},
	"sourceSize": {"w":28,"h":32}
},
{
	"filename": "candy/yellow6",
	"frame": {"x":860,"y":0,"w":28,"h":32},
	"rotated": false,
	"trimmed": false,
	"spriteSourceSize": {"x":0,"y":0,"w":28,"h":32},
	"sourceSize": {"w":28,"h":32}
},
{
	"filename": "car/car1",
	"frame": {"x":0,"y":64,"w":48,"h":32},
	"rotated": false,
	"trimmed": false,
	"spriteSourceSize": {"x":0,"y":0,"w":48,"h":32},
	"sourceSize": {"w":48,"h":32}
},
{
	"filename": "car/car2",
	"frame": {"x":48,"y":64,"w":48,"h":32},
	"rotated": false,
	"trimmed": false,
	"spriteSourceSize": {"x":0,"y":0,"w":48,"h":32},
	"sourceSize": {"w":48,"h":32}
},
{
	"filename": "car/car3",
	"frame": {"x":144,"y":64,"w":48,"h":32},
	"rotated": false,
	"trimmed": false,
	"spriteSourceSize": {"x":0,"y":0,"w":48,"h":32},
	"sourceSize": {"w":48,"h":32}
},
{
	"filename": "car/car4",
	"frame": {"x":96,"y":64,"w":48,"h":32},
	"rotated": false,
	"trimmed": false,
	"spriteSourceSize": {"x":0,"y":0,"w":48,"h":32},
	"sourceSize": {"w":48,"h":32}
},
{
	"filename": "car/crushed",
	"frame": {"x":192,"y":64,"w":48,"h":32},
	"rotated": false,
	"trimmed": false,
	"spriteSourceSize": {"x":0,"y":0,"w":48,"h":32},
	"sourceSize": {"w":48,"h":32}
},
{
	"filename": "exit",
	"frame": {"x":58,"y":0,"w":24,"h":24},
	"rotated": false,
	"trimmed": false,
	"spriteSourceSize": {"x":0,"y":0,"w":24,"h":24},
	"sourceSize": {"w":24,"h":24}
},
{
	"filename": "flag",
	"frame": {"x":128,"y":32,"w":32,"h":32},
	"rotated": false,
	"trimmed": false,
	"spriteSourceSize": {"x":0,"y":0,"w":32,"h":32},
	"sourceSize": {"w":32,"h":32}
},
{
	"filename": "heart",
	"frame": {"x":18,"y":0,"w":16,"h":16},
	"rotated": false,
	"trimmed": false,
	"spriteSourceSize": {"x":0,"y":0,"w":16,"h":16},
	"sourceSize": {"w":16,"h":16}
},
{
	"filename": "liar/flat",
	"frame": {"x":96,"y":32,"w":32,"h":32},
	"rotated": false,
	"trimmed": false,
	"spriteSourceSize": {"x":0,"y":0,"w":32,"h":32},
	"sourceSize": {"w":32,"h":32}
},
{
	"filename": "liar/walk",
	"frame": {"x":944,"y":0,"w":32,"h":32},
	"rotated": false,
	"trimmed": false,
	"spriteSourceSize": {"x":0,"y":0,"w":32,"h":32},
	"sourceSize": {"w":32,"h":32}
},
{
	"filename": "pad/a",
	"frame": {"x":804,"y":192,"w":100,"h":100},
	"rotated": false,
	"trimmed": false,
	"spriteSourceSize": {"x":0,"y":0,"w":100,"h":100},
	"sourceSize": {"w":100,"h":100}
},
{
	"filename": "pad/default",
	"frame": {"x":400,"y":492,"w":200,"h":200},
	"rotated": false,
	"trimmed": false,
	"spriteSourceSize": {"x":0,"y":0,"w":200,"h":200},
	"sourceSize": {"w":200,"h":200}
},
{
	"filename": "pad/down",
	"frame": {"x":800,"y":492,"w":200,"h":200},
	"rotated": false,
	"trimmed": false,
	"spriteSourceSize": {"x":0,"y":0,"w":200,"h":200},
	"sourceSize": {"w":200,"h":200}
},
{
	"filename": "pad/left-down",
	"frame": {"x":600,"y":492,"w":200,"h":200},
	"rotated": false,
	"trimmed": false,
	"spriteSourceSize": {"x":0,"y":0,"w":200,"h":200},
	"sourceSize": {"w":200,"h":200}
},
{
	"filename": "pad/left-up",
	"frame": {"x":200,"y":492,"w":200,"h":200},
	"rotated": false,
	"trimmed": false,
	"spriteSourceSize": {"x":0,"y":0,"w":200,"h":200},
	"sourceSize": {"w":200,"h":200}
},
{
	"filename": "pad/left",
	"frame": {"x":0,"y":492,"w":200,"h":200},
	"rotated": false,
	"trimmed": false,
	"spriteSourceSize": {"x":0,"y":0,"w":200,"h":200},
	"sourceSize": {"w":200,"h":200}
},
{
	"filename": "pad/right-down",
	"frame": {"x":360,"y":292,"w":200,"h":200},
	"rotated": false,
	"trimmed": false,
	"spriteSourceSize": {"x":0,"y":0,"w":200,"h":200},
	"sourceSize": {"w":200,"h":200}
},
{
	"filename": "pad/right-up",
	"frame": {"x":760,"y":292,"w":200,"h":200},
	"rotated": false,
	"trimmed": false,
	"spriteSourceSize": {"x":0,"y":0,"w":200,"h":200},
	"sourceSize": {"w":200,"h":200}
},
{
	"filename": "pad/right",
	"frame": {"x":560,"y":292,"w":200,"h":200},
	"rotated": false,
	"trimmed": false,
	"spriteSourceSize": {"x":0,"y":0,"w":200,"h":200},
	"sourceSize": {"w":200,"h":200}
},
{
	"filename": "pad/up-button",
	"frame": {"x":704,"y":192,"w":100,"h":100},
	"rotated": false,
	"trimmed": false,
	"spriteSourceSize": {"x":0,"y":0,"w":100,"h":100},
	"sourceSize": {"w":100,"h":100}
},
{
	"filename": "pad/up",
	"frame": {"x":160,"y":292,"w":200,"h":200},
	"rotated": false,
	"trimmed": false,
	"spriteSourceSize": {"x":0,"y":0,"w":200,"h":200},
	"sourceSize": {"w":200,"h":200}
},
{
	"filename": "player",
	"frame": {"x":0,"y":292,"w":160,"h":160},
	"rotated": false,
	"trimmed": false,
	"spriteSourceSize": {"x":0,"y":0,"w":160,"h":160},
	"sourceSize": {"w":160,"h":160}
},
{
	"filename": "powerup/bear",
	"frame": {"x":512,"y":32,"w":32,"h":32},
	"rotated": false,
	"trimmed": false,
	"spriteSourceSize": {"x":0,"y":0,"w":32,"h":32},
	"sourceSize": {"w":32,"h":32}
},
{
	"filename": "powerup/butterfly1",
	"frame": {"x":448,"y":32,"w":32,"h":32},
	"rotated": false,
	"trimmed": false,
	"spriteSourceSize": {"x":0,"y":0,"w":32,"h":32},
	"sourceSize": {"w":32,"h":32}
},
{
	"filename": "powerup/butterfly2",
	"frame": {"x":416,"y":32,"w":32,"h":32},
	"rotated": false,
	"trimmed": false,
	"spriteSourceSize": {"x":0,"y":0,"w":32,"h":32},
	"sourceSize": {"w":32,"h":32}
},
{
	"filename": "powerup/butterfly3",
	"frame": {"x":320,"y":32,"w":32,"h":32},
	"rotated": false,
	"trimmed": false,
	"spriteSourceSize": {"x":0,"y":0,"w":32,"h":32},
	"sourceSize": {"w":32,"h":32}
},
{
	"filename": "powerup/flower",
	"frame": {"x":384,"y":32,"w":32,"h":32},
	"rotated": false,
	"trimmed": false,
	"spriteSourceSize": {"x":0,"y":0,"w":32,"h":32},
	"sourceSize": {"w":32,"h":32}
},
{
	"filename": "powerup/robot1",
	"frame": {"x":352,"y":32,"w":32,"h":32},
	"rotated": false,
	"trimmed": false,
	"spriteSourceSize": {"x":0,"y":0,"w":32,"h":32},
	"sourceSize": {"w":32,"h":32}
},
{
	"filename": "powerup/robot2",
	"frame": {"x":576,"y":32,"w":32,"h":32},
	"rotated": false,
	"trimmed": false,
	"spriteSourceSize": {"x":0,"y":0,"w":32,"h":32},
	"sourceSize": {"w":32,"h":32}
},
{
	"filename": "powerup/robot3",
	"frame": {"x":544,"y":32,"w":32,"h":32},
	"rotated": false,
	"trimmed": false,
	"spriteSourceSize": {"x":0,"y":0,"w":32,"h":32},
	"sourceSize": {"w":32,"h":32}
},
{
	"filename": "profile",
	"frame": {"x":34,"y":0,"w":24,"h":24},
	"rotated": false,
	"trimmed": false,
	"spriteSourceSize": {"x":0,"y":0,"w":24,"h":24},
	"sourceSize": {"w":24,"h":24}
},
{
	"filename": "sophia/bend",
	"frame": {"x":288,"y":32,"w":32,"h":32},
	"rotated": false,
	"trimmed": false,
	"spriteSourceSize": {"x":0,"y":0,"w":32,"h":32},
	"sourceSize": {"w":32,"h":32}
},
{
	"filename": "sophia/bendBig",
	"frame": {"x":560,"y":64,"w":64,"h":64},
	"rotated": false,
	"trimmed": false,
	"spriteSourceSize": {"x":0,"y":0,"w":64,"h":64},
	"sourceSize": {"w":64,"h":64}
},
{
	"filename": "sophia/bendSuper",
	"frame": {"x":752,"y":64,"w":64,"h":64},
	"rotated": false,
	"trimmed": false,
	"spriteSourceSize": {"x":0,"y":0,"w":64,"h":64},
	"sourceSize": {"w":64,"h":64}
},
{
	"filename": "sophia/climb1",
	"frame": {"x":256,"y":32,"w":32,"h":32},
	"rotated": false,
	"trimmed": false,
	"spriteSourceSize": {"x":0,"y":0,"w":32,"h":32},
	"sourceSize": {"w":32,"h":32}
},
{
	"filename": "sophia/climb2",
	"frame": {"x":32,"y":32,"w":32,"h":32},
	"rotated": false,
	"trimmed": false,
	"spriteSourceSize": {"x":0,"y":0,"w":32,"h":32},
	"sourceSize": {"w":32,"h":32}
},
{
	"filename": "sophia/climbBig1",
	"frame": {"x":128,"y":128,"w":64,"h":64},
	"rotated": false,
	"trimmed": false,
	"spriteSourceSize": {"x":0,"y":0,"w":64,"h":64},
	"sourceSize": {"w":64,"h":64}
},
{
	"filename": "sophia/climbBig2",
	"frame": {"x":256,"y":128,"w":64,"h":64},
	"rotated": false,
	"trimmed": false,
	"spriteSourceSize": {"x":0,"y":0,"w":64,"h":64},
	"sourceSize": {"w":64,"h":64}
},
{
	"filename": "sophia/climbSuper1",
	"frame": {"x":384,"y":128,"w":64,"h":64},
	"rotated": false,
	"trimmed": false,
	"spriteSourceSize": {"x":0,"y":0,"w":64,"h":64},
	"sourceSize": {"w":64,"h":64}
},
{
	"filename": "sophia/climbSuper2",
	"frame": {"x":688,"y":64,"w":64,"h":64},
	"rotated": false,
	"trimmed": false,
	"spriteSourceSize": {"x":0,"y":0,"w":64,"h":64},
	"sourceSize": {"w":64,"h":64}
},
{
	"filename": "sophia/death",
	"frame": {"x":0,"y":32,"w":32,"h":32},
	"rotated": false,
	"trimmed": false,
	"spriteSourceSize": {"x":0,"y":0,"w":32,"h":32},
	"sourceSize": {"w":32,"h":32}
},
{
	"filename": "sophia/half",
	"frame": {"x":272,"y":64,"w":32,"h":64},
	"rotated": false,
	"trimmed": false,
	"spriteSourceSize": {"x":0,"y":0,"w":32,"h":64},
	"sourceSize": {"w":32,"h":64}
},
{
	"filename": "sophia/jump",
	"frame": {"x":192,"y":32,"w":32,"h":32},
	"rotated": false,
	"trimmed": false,
	"spriteSourceSize": {"x":0,"y":0,"w":32,"h":32},
	"sourceSize": {"w":32,"h":32}
},
{
	"filename": "sophia/jumpBig",
	"frame": {"x":816,"y":64,"w":64,"h":64},
	"rotated": false,
	"trimmed": false,
	"spriteSourceSize": {"x":0,"y":0,"w":64,"h":64},
	"sourceSize": {"w":64,"h":64}
},
{
	"filename": "sophia/jumpSuper",
	"frame": {"x":0,"y":128,"w":64,"h":64},
	"rotated": false,
	"trimmed": false,
	"spriteSourceSize": {"x":0,"y":0,"w":64,"h":64},
	"sourceSize": {"w":64,"h":64}
},
{
	"filename": "sophia/stand",
	"frame": {"x":64,"y":32,"w":32,"h":32},
	"rotated": false,
	"trimmed": false,
	"spriteSourceSize": {"x":0,"y":0,"w":32,"h":32},
	"sourceSize": {"w":32,"h":32}
},
{
	"filename": "sophia/standBig",
	"frame": {"x":880,"y":64,"w":64,"h":64},
	"rotated": false,
	"trimmed": false,
	"spriteSourceSize": {"x":0,"y":0,"w":64,"h":64},
	"sourceSize": {"w":64,"h":64}
},
{
	"filename": "sophia/standSuper",
	"frame": {"x":320,"y":128,"w":64,"h":64},
	"rotated": false,
	"trimmed": false,
	"spriteSourceSize": {"x":0,"y":0,"w":64,"h":64},
	"sourceSize": {"w":64,"h":64}
},
{
	"filename": "sophia/turn",
	"frame": {"x":640,"y":32,"w":32,"h":32},
	"rotated": false,
	"trimmed": false,
	"spriteSourceSize": {"x":0,"y":0,"w":32,"h":32},
	"sourceSize": {"w":32,"h":32}
},
{
	"filename": "sophia/turnBig",
	"frame": {"x":64,"y":128,"w":64,"h":64},
	"rotated": false,
	"trimmed": false,
	"spriteSourceSize": {"x":0,"y":0,"w":64,"h":64},
	"sourceSize": {"w":64,"h":64}
},
{
	"filename": "sophia/turnSuper",
	"frame": {"x":192,"y":128,"w":64,"h":64},
	"rotated": false,
	"trimmed": false,
	"spriteSourceSize": {"x":0,"y":0,"w":64,"h":64},
	"sourceSize": {"w":64,"h":64}
},
{
	"filename": "sophia/walk1",
	"frame": {"x":704,"y":32,"w":32,"h":32},
	"rotated": false,
	"trimmed": false,
	"spriteSourceSize": {"x":0,"y":0,"w":32,"h":32},
	"sourceSize": {"w":32,"h":32}
},
{
	"filename": "sophia/walk2",
	"frame": {"x":928,"y":32,"w":32,"h":32},
	"rotated": false,
	"trimmed": false,
	"spriteSourceSize": {"x":0,"y":0,"w":32,"h":32},
	"sourceSize": {"w":32,"h":32}
},
{
	"filename": "sophia/walk3",
	"frame": {"x":896,"y":32,"w":32,"h":32},
	"rotated": false,
	"trimmed": false,
	"spriteSourceSize": {"x":0,"y":0,"w":32,"h":32},
	"sourceSize": {"w":32,"h":32}
},
{
	"filename": "sophia/walkBig1",
	"frame": {"x":432,"y":64,"w":64,"h":64},
	"rotated": false,
	"trimmed": false,
	"spriteSourceSize": {"x":0,"y":0,"w":64,"h":64},
	"sourceSize": {"w":64,"h":64}
},
{
	"filename": "sophia/walkBig2",
	"frame": {"x":304,"y":64,"w":64,"h":64},
	"rotated": false,
	"trimmed": false,
	"spriteSourceSize": {"x":0,"y":0,"w":64,"h":64},
	"sourceSize": {"w":64,"h":64}
},
{
	"filename": "sophia/walkBig3",
	"frame": {"x":624,"y":64,"w":64,"h":64},
	"rotated": false,
	"trimmed": false,
	"spriteSourceSize": {"x":0,"y":0,"w":64,"h":64},
	"sourceSize": {"w":64,"h":64}
},
{
	"filename": "sophia/walkSuper1",
	"frame": {"x":496,"y":64,"w":64,"h":64},
	"rotated": false,
	"trimmed": false,
	"spriteSourceSize": {"x":0,"y":0,"w":64,"h":64},
	"sourceSize": {"w":64,"h":64}
},
{
	"filename": "sophia/walkSuper2",
	"frame": {"x":368,"y":64,"w":64,"h":64},
	"rotated": false,
	"trimmed": false,
	"spriteSourceSize": {"x":0,"y":0,"w":64,"h":64},
	"sourceSize": {"w":64,"h":64}
},
{
	"filename": "sophia/walkSuper3",
	"frame": {"x":576,"y":128,"w":64,"h":64},
	"rotated": false,
	"trimmed": false,
	"spriteSourceSize": {"x":0,"y":0,"w":64,"h":64},
	"sourceSize": {"w":64,"h":64}
}],
"meta": {
	"app": "https://www.codeandweb.com/texturepacker",
	"version": "1.0",
	"image": "game-sprites.png",
	"format": "RGBA8888",
	"size": {"w":1000,"h":692},
	"scale": "1",
	"smartupdate": "$TexturePacker:SmartUpdate:0f7ad40ab8e843818ca780c621ca8830:8d874dbf207de88fb473ae492792c035:6c31e76162759595c120c84b8850a36e$"
}
}
